holos_sdk/__init__.py
holos_sdk/holos_a2a_client.py
holos_sdk/holos_a2a_client_factory.py
holos_sdk/holos_request_handler.py
holos_sdk/logging_config.py
holos_sdk/plant_tracer.py
holos_sdk/types.py
holos_sdk/utils.py
holos_sdk-0.2.13.dist-info/METADATA
holos_sdk-0.2.13.dist-info/WHEEL
holos_sdk-0.2.13.dist-info/top_level.txt
holos_sdk-0.2.13.dist-info/RECORD
